		{
            "scheduleBook" : [
                {
                    "name": "Theo",
                    "MDemail": "rabinovich@healthpartners.com",
	                "DOB" : "12202016",
	                "NextAppt" : "01202016",
	                "NextSchoolConf" : "11162015e"
                },
                {
                    "name": "Suvi",
                    "MDemail": "rabinovich@healthpartners.com",
	                "DOB" : "03282008",
	                "NextAppt" : "02202016",
	                "NextSchoolConf" : "11222015"
                },
                {
                    "name": "Judah",
                    "MDemail": "rabinovich@healthpartners.com",
	                "DOB" : "04102014",
	                "NextAppt" : "05212010",
	                "NextSchoolConf" : "11252015"
                },
                {
                    "name": "Russell",
                    "MDemail": "rabinovich@healthpartners.com",
	                "DOB" : "04102014",
	                "NextAppt" : "03202016",
	                "NextSchoolConf" : "None"
                }

            ]
        }